{
    "bytes_10_000": {
        "run_0": {
            "n_ms_native": "    0",
            "n_ms_wasm": "    1"
        },
        "run_1": {
            "n_ms_native": "    0",
            "n_ms_wasm": "    0"
        },
        "run_2": {
            "n_ms_native": "    0",
            "n_ms_wasm": "    0"
        }
    },
    "bytes_100_000": {
        "run_0": {
            "n_ms_native": "    0",
            "n_ms_wasm": "    0"
        },
        "run_1": {
            "n_ms_native": "    0",
            "n_ms_wasm": "    0"
        },
        "run_2": {
            "n_ms_native": "    0",
            "n_ms_wasm": "    0"
        }
    },
    "bytes_1_000_000": {
        "run_0": {
            "n_ms_native": "    5",
            "n_ms_wasm": "    2"
        },
        "run_1": {
            "n_ms_native": "    2",
            "n_ms_wasm": "    0"
        },
        "run_2": {
            "n_ms_native": "    2",
            "n_ms_wasm": "    0"
        }
    },
    "bytes_10_000_000": {
        "run_0": {
            "n_ms_native": "   44",
            "n_ms_wasm": "    8"
        },
        "run_1": {
            "n_ms_native": "   21",
            "n_ms_wasm": "    5"
        },
        "run_2": {
            "n_ms_native": "   21",
            "n_ms_wasm": "    5"
        }
    },
    "bytes_100_000_000": {
        "run_0": {
            "n_ms_native": "  237",
            "n_ms_wasm": "  104"
        },
        "run_1": {
            "n_ms_native": "  210",
            "n_ms_wasm": "   58"
        },
        "run_2": {
            "n_ms_native": "  211",
            "n_ms_wasm": "   53"
        }
    },
    "bytes_1_000_000_000": {
        "run_0": {
            "n_ms_native": " 2104",
            "n_ms_wasm": " 1018"
        },
        "run_1": {
            "n_ms_native": " 2102",
            "n_ms_wasm": "  562"
        },
        "run_2": {
            "n_ms_native": " 2096",
            "n_ms_wasm": "  534"
        }
    },
    "bytes_2_097_152_000": {
        "run_0": {
            "n_ms_native": " 4392",
            "n_ms_wasm": " 1772"
        },
        "run_1": {
            "n_ms_native": " 4392",
            "n_ms_wasm": " 1169"
        },
        "run_2": {
            "n_ms_native": " 4392",
            "n_ms_wasm": " 1120"
        }
    }
}